{
  "_class": "symbolInstance",
  "booleanOperation": -1,
  "clippingMaskMode": 0,
  "do_objectID": "5F2568CD-368D-4D31-A863-4CE975F5406E",
  "exportOptions": {
    "_class": "exportOptions",
    "exportFormats": [
    ],
    "includedLayerIds": [
    ],
    "layerOptions": 0,
    "shouldTrim": false
  },
  "frame": {
    "_class": "rect",
    "constrainProportions": false,
    "height": 48,
    "width": 102,
    "x": 298,
    "y": 422
  },
  "hasClippingMask": false,
  "horizontalSpacing": 0,
  "isFixedToViewport": false,
  "isFlippedHorizontal": false,
  "isFlippedVertical": false,
  "isLocked": false,
  "isVisible": true,
  "layerListExpandedType": 0,
  "name": "Atoms/Buttons Copy",
  "nameIsFixed": false,
  "overrideValues": [
    {
      "_class": "overrideValue",
      "overrideName": "A1120CE1-F211-44BC-A273-3EB54FEA1141_stringValue",
      "value": "Share"
    },
    {
      "_class": "overrideValue",
      "overrideName": "FB891EB3-5E0D-42A2-8223-528D7E557BE0_layerStyle",
      "value": "F36F0DC1-F675-495E-BEF5-98694E71D38B"
    },
    {
      "_class": "overrideValue",
      "overrideName": "A1120CE1-F211-44BC-A273-3EB54FEA1141_textStyle",
      "value": "A0AAA240-895D-4F2C-A025-5F56195A5703"
    }
  ],
  "resizingConstraint": 63,
  "resizingType": 0,
  "rotation": 0,
  "scale": 1,
  "shouldBreakMaskChain": false,
  "style": {
    "_class": "style",
    "endMarkerType": 0,
    "miterLimit": 10,
    "startMarkerType": 0,
    "windingRule": 1
  },
  "symbolID": "81AA26A7-FA53-4BB4-8989-10F26714C65F",
  "verticalSpacing": 0
}