{
  "_class": "artboard",
  "backgroundColor": {
    "_class": "color",
    "alpha": 1,
    "blue": 1,
    "green": 1,
    "red": 1
  },
  "booleanOperation": -1,
  "clippingMaskMode": 0,
  "do_objectID": "8024850B-22AE-4F0E-B6BC-10977E7A6F3A",
  "exportOptions": {
    "_class": "exportOptions",
    "exportFormats": [
      {
        "_class": "exportFormat",
        "absoluteSize": 0,
        "fileFormat": "png",
        "name": "",
        "namingScheme": 0,
        "scale": 1,
        "visibleScaleType": 0
      }
    ],
    "includedLayerIds": [
    ],
    "layerOptions": 0,
    "shouldTrim": false
  },
  "frame": {
    "_class": "rect",
    "constrainProportions": false,
    "height": 11647,
    "width": 5445,
    "x": -5429,
    "y": -3948
  },
  "groupLayout": {
    "_class": "MSImmutableFreeformGroupLayout"
  },
  "hasBackgroundColor": true,
  "hasClickThrough": false,
  "hasClippingMask": false,
  "horizontalRulerData": {
    "_class": "rulerData",
    "base": 0,
    "guides": [
    ]
  },
  "includeBackgroundColorInExport": true,
  "includeInCloudUpload": true,
  "isFixedToViewport": false,
  "isFlippedHorizontal": false,
  "isFlippedVertical": false,
  "isFlowHome": false,
  "isLocked": false,
  "isVisible": true,
  "layerListExpandedType": 2,
  "layers": [
    {
      "class": "bitmap",
      "id": "E3EFC03C-988A-4BA5-B766-EAD2CC57C667"
    },
    {
      "class": "shapePath",
      "id": "5AD2E4F9-03ED-49F6-98CC-E930761D2322"
    },
    {
      "class": "shapePath",
      "id": "C3CED507-CBAF-4316-9E84-8993A8125837"
    },
    {
      "class": "shapePath",
      "id": "7E10A960-AB71-4094-B997-D1A3FD3C9F25"
    },
    {
      "class": "shapePath",
      "id": "F0F37E9A-819E-4FD7-847F-E07A5FC90A2B"
    },
    {
      "class": "shapePath",
      "id": "BB26A3B3-6172-4A7B-8F41-851EB50A07ED"
    },
    {
      "class": "shapePath",
      "id": "A5D9708A-5B47-4E49-91ED-FE4ADEBDF064"
    },
    {
      "class": "group",
      "id": "1AB68615-145A-4B26-AFF8-EA69AF6A3875"
    },
    {
      "class": "group",
      "id": "372E7D00-3E9E-4BC8-B7AF-737F55FB30B4"
    },
    {
      "class": "group",
      "id": "EAF12B4F-DDC6-4EBA-A57D-F8DE9FF2938C"
    },
    {
      "class": "group",
      "id": "691CF370-6E20-4AE6-A5CA-911A7E8FE0DC"
    },
    {
      "class": "shapePath",
      "id": "CAAE893C-BFF7-4694-ABDE-2A99C117C570"
    },
    {
      "class": "group",
      "id": "922DA292-E80F-49D7-AD9E-ADE7E3922A29"
    },
    {
      "class": "group",
      "id": "24063829-BF3C-4EF7-8F8B-37AFF7457613"
    },
    {
      "class": "group",
      "id": "57264A98-2A33-4F92-97CA-B7F194BB412C"
    },
    {
      "class": "shapePath",
      "id": "BEC80F02-3CE3-48DE-AE6A-147C32E0D247"
    },
    {
      "class": "group",
      "id": "73D55885-1F12-4A74-ABED-C7C52E002AF6"
    },
    {
      "class": "shapePath",
      "id": "577259D8-9E17-428E-B269-75184C462BE4"
    },
    {
      "class": "shapePath",
      "id": "334B3176-5418-4BBC-9346-B55B198EBAA0"
    },
    {
      "class": "shapePath",
      "id": "628B570B-654E-433C-97DF-304DB8201365"
    },
    {
      "class": "group",
      "id": "0F2E841C-71A7-4014-91A5-C191A89EB694"
    }
  ],
  "name": "Artboard",
  "nameIsFixed": false,
  "resizesContent": false,
  "resizingConstraint": 63,
  "resizingType": 0,
  "rotation": 0,
  "shouldBreakMaskChain": true,
  "style": {
    "_class": "style",
    "endMarkerType": 0,
    "miterLimit": 10,
    "startMarkerType": 0,
    "windingRule": 1
  },
  "verticalRulerData": {
    "_class": "rulerData",
    "base": 0,
    "guides": [
    ]
  }
}