{
  "_class": "group",
  "booleanOperation": 0,
  "clippingMaskMode": 0,
  "do_objectID": "CD9F39A1-72E7-4F39-A516-17C7F75B2400",
  "exportOptions": {
    "_class": "exportOptions",
    "do_objectID": "95D93014-B91A-40C9-9EC8-DBCC2C6D8BFD",
    "exportFormats": [
    ],
    "includedLayerIds": [
    ],
    "layerOptions": 0,
    "shouldTrim": false
  },
  "frame": {
    "_class": "rect",
    "constrainProportions": false,
    "do_objectID": "21A13A66-A6A1-4299-AD3D-7816D9515BF9",
    "height": 291.9999999999997,
    "width": 399.0000000000001,
    "x": 3,
    "y": 0
  },
  "groupLayout": {
    "_class": "MSImmutableFreeformGroupLayout",
    "do_objectID": "2CA0C29B-52CB-4616-B2AC-E17D759FB51A"
  },
  "hasClickThrough": false,
  "hasClippingMask": false,
  "isFixedToViewport": false,
  "isFlippedHorizontal": false,
  "isFlippedVertical": false,
  "isLocked": false,
  "isVisible": true,
  "layerListExpandedType": 2,
  "layers": [
    {
      "class": "rectangle",
      "id": "8D9CDEBF-BA67-4964-98AE-FD58DCBECB71"
    }
  ],
  "name": "Graph / Background",
  "nameIsFixed": true,
  "resizingConstraint": 63,
  "resizingType": 0,
  "rotation": 0,
  "shouldBreakMaskChain": false,
  "style": {
    "_class": "style",
    "do_objectID": "7ED2BDDA-4E87-42C5-95FB-8D08C77E5EF8",
    "endMarkerType": 0,
    "miterLimit": 10,
    "startMarkerType": 0,
    "windingRule": 1
  }
}