{
  "_class": "group",
  "booleanOperation": -1,
  "clippingMaskMode": 0,
  "do_objectID": "44B93DBE-839D-4AEB-B891-F610E2C4D20D",
  "exportOptions": {
    "_class": "exportOptions",
    "do_objectID": "2380B84C-DF8F-4A7F-AEB9-82F371EBF23F",
    "exportFormats": [
    ],
    "includedLayerIds": [
    ],
    "layerOptions": 0,
    "shouldTrim": false
  },
  "frame": {
    "_class": "rect",
    "constrainProportions": false,
    "do_objectID": "5575A898-A6FE-4CD1-A23F-0AFB0DFB5BD5",
    "height": 49,
    "width": 164,
    "x": 0,
    "y": 107
  },
  "groupLayout": {
    "_class": "MSImmutableFreeformGroupLayout",
    "do_objectID": "8FF72C3C-8967-4780-A6A6-78FFBBA3CED6"
  },
  "hasClickThrough": false,
  "hasClippingMask": false,
  "isFixedToViewport": false,
  "isFlippedHorizontal": false,
  "isFlippedVertical": false,
  "isLocked": false,
  "isVisible": true,
  "layerListExpandedType": 2,
  "layers": [
    {
      "class": "symbolInstance",
      "id": "9E62C5F9-FDF8-4B6B-B159-B2DB5EE2CD48"
    }
  ],
  "name": "Group 5",
  "nameIsFixed": false,
  "resizingConstraint": 63,
  "resizingType": 0,
  "rotation": 0,
  "shouldBreakMaskChain": false,
  "style": {
    "_class": "style",
    "do_objectID": "E2053931-E2CA-47A4-AC79-BF1E3DAD02D9",
    "endMarkerType": 0,
    "miterLimit": 10,
    "startMarkerType": 0,
    "windingRule": 1
  }
}