{
  "_class": "symbolInstance",
  "booleanOperation": -1,
  "clippingMaskMode": 0,
  "do_objectID": "FAA83F0B-03E1-4F4B-B62D-27638CE2BD9D",
  "exportOptions": {
    "_class": "exportOptions",
    "do_objectID": "EA491B82-B7BB-4972-99F3-B09F96AC1551",
    "exportFormats": [
    ],
    "includedLayerIds": [
    ],
    "layerOptions": 0,
    "shouldTrim": false
  },
  "frame": {
    "_class": "rect",
    "constrainProportions": false,
    "do_objectID": "83498A3C-273A-4838-AEBC-005F8F36A0EE",
    "height": 48,
    "width": 328,
    "x": 0,
    "y": 435
  },
  "hasClippingMask": false,
  "horizontalSpacing": 0,
  "isFixedToViewport": false,
  "isFlippedHorizontal": false,
  "isFlippedVertical": false,
  "isLocked": false,
  "isVisible": true,
  "layerListExpandedType": 0,
  "name": "Atoms/Buttons",
  "nameIsFixed": false,
  "overrideValues": [
  ],
  "resizingConstraint": 63,
  "resizingType": 0,
  "rotation": 0,
  "scale": 1,
  "shouldBreakMaskChain": false,
  "style": {
    "_class": "style",
    "do_objectID": "4D69782A-39FA-46FF-B2B8-65C01250B05F",
    "endMarkerType": 0,
    "miterLimit": 10,
    "startMarkerType": 0,
    "windingRule": 1
  },
  "symbolID": "81AA26A7-FA53-4BB4-8989-10F26714C65F",
  "verticalSpacing": 0
}